[
  {
    "序號": 1,
    "產品標題": "AirPods 第 3 代搭配 MagSafe 充電盒 (整修品)",
    "產品售價": "NT$4,690",
    "產品概覽": "AirPods 第 3 代搭配 MagSafe 充電盒 (整修品)",
    "產品URL": "https://www.apple.com/tw/shop/refurbished/accessories"
  },
  {
    "序號": 2,
    "產品標題": "AirPods Pro 2 搭配 MagSafe 充電盒 (USB-C，整修品)",
    "產品售價": "NT$6,390",
    "產品概覽": "AirPods Pro 2 搭配 MagSafe 充電盒 (USB-C，整修品)",
    "產品URL": "https://www.apple.com/tw/shop/refurbished/accessories"
  },
  {
    "序號": 3,
    "產品標題": "HomePod (第 2 代) - 午夜色 (整修品)",
    "產品售價": "NT$7,900",
    "產品概覽": "HomePod (第 2 代) - 午夜色 (整修品)",
    "產品URL": "https://www.apple.com/tw/shop/refurbished/accessories"
  },
  {
    "序號": 4,
    "產品標題": "HomePod (第 2 代) - 白色 (整修品)",
    "產品售價": "NT$7,900",
    "產品概覽": "HomePod (第 2 代) - 白色 (整修品)",
    "產品URL": "https://www.apple.com/tw/shop/refurbished/accessories"
  }
]